setup.py
sampler_distributions_pkg/Binomialdistribution.py
sampler_distributions_pkg/Gaussiandistribution.py
sampler_distributions_pkg/Generaldistribution.py
sampler_distributions_pkg/__init__.py
sampler_distributions_pkg.egg-info/PKG-INFO
sampler_distributions_pkg.egg-info/SOURCES.txt
sampler_distributions_pkg.egg-info/dependency_links.txt
sampler_distributions_pkg.egg-info/not-zip-safe
sampler_distributions_pkg.egg-info/top_level.txt