Metadata-Version: 1.0
Name: sampler-distributions-pkg
Version: 0.1
Summary: Gaussian distributions
Home-page: UNKNOWN
Author: Daniel Bailey
Author-email: UNKNOWN
License: UNKNOWN
Platform: UNKNOWN
